[
    {
        // name of item
        "title": ,
        // 3D object
        "model": ,
        // desc
        "description": ,
        // real world data
        "intelligence": 
    },
    {
        // name of item
        "title": ,
        // 3D object
        "model": ,
        // desc
        "description": ,
        // real world data
        "intelligence": 
    },
    {
        // name of item
        "title": ,
        // 3D object
        "model": ,
        // desc
        "description": ,
        // real world data
        "intelligence": 
    },
    {
        // name of item
        "title": ,
        // 3D object
        "model": ,
        // desc
        "description": ,
        // real world data
        "intelligence": 
    },
    {
        // name of item
        "title": ,
        // 3D object
        "model": ,
        // desc
        "description": ,
        // real world data
        "intelligence": 
    },
]